[{"line":1,"elements":[{"start_timestamp":"2022-06-27T16:22:56.999Z","line":5,"name":"User logins on the sauce demo page","description":"","id":"user-should-be-login-with-valid-credential;user-logins-on-the-sauce-demo-page","type":"scenario","keyword":"Scenario","steps":[{"result":{"duration":12159200000,"status":"passed"},"line":6,"name":"User is on the login page","match":{"location":"demo.sauce.stepDefinitions.LoginStep.userIsOnTheLoginPage()"},"keyword":"Given "},{"result":{"duration":104378000,"status":"passed"},"line":7,"name":"User enters \"standard_user\" and \"secret_sauce\"","match":{"arguments":[{"val":"\"standard_user\"","offset":12},{"val":"\"secret_sauce\"","offset":32}],"location":"demo.sauce.stepDefinitions.LoginStep.user_enters_and(java.lang.String,java.lang.String)"},"keyword":"Given "},{"result":{"duration":43351000,"status":"passed"},"line":8,"name":"User clicks the login button","match":{"location":"demo.sauce.stepDefinitions.LoginStep.user_clicks_the_login_button()"},"keyword":"When "},{"result":{"duration":28896000,"status":"passed"},"line":9,"name":"User should see the home page","match":{"location":"demo.sauce.stepDefinitions.LoginStep.user_should_see_the_home_page()"},"keyword":"Then "}],"tags":[{"name":"@login"}]}],"name":"User Should be login with valid credential","description":"  User Story: User should be login with valid credential","id":"user-should-be-login-with-valid-credential","keyword":"Feature","uri":"file:src/test/resources/features/login.feature","tags":[]}]